dserver_retrieve_plugin_mongo/__init__.py
dserver_retrieve_plugin_mongo/config.py
dserver_retrieve_plugin_mongo/utils_retrieve.py
dserver_retrieve_plugin_mongo/version.py
dserver_retrieve_plugin_mongo-0.4.2.dist-info/LICENSE.rst
dserver_retrieve_plugin_mongo-0.4.2.dist-info/METADATA
dserver_retrieve_plugin_mongo-0.4.2.dist-info/WHEEL
dserver_retrieve_plugin_mongo-0.4.2.dist-info/entry_points.txt
dserver_retrieve_plugin_mongo-0.4.2.dist-info/top_level.txt
dserver_retrieve_plugin_mongo-0.4.2.dist-info/RECORD
