Metadata-Version: 2.1
Name: dserver-retrieve-plugin-mongo
Version: 0.4.2
Summary: Retrieve plugin for dserver using mongodb
Author-email: Tjelvar Olsson <tjelvar.olsson@gmail.com>, "Johannes L. Hörmann" <johannes.laurin@gmail.com>
Project-URL: Documentation, https://github.com/jic-dtool/dserver-retrieve-plugin-mongo/blob/main/README.rst
Project-URL: Repository, https://github.com/jic-dtool/dserver-retrieve-plugin-mongo
Project-URL: Changelog, https://github.com/jic-dtool/dserver-retrieve-plugin-mongo/blob/main/CHANGELOG.rst
License-File: LICENSE.rst
Requires-Dist: pymongo
Requires-Dist: dtoolcore >=3.18.0
Requires-Dist: dservercore
Provides-Extra: test
Requires-Dist: dservercore ; extra == 'test'
Requires-Dist: dserver-search-plugin-mongo ; extra == 'test'
Requires-Dist: pytest ; extra == 'test'
Requires-Dist: pytest-cov ; extra == 'test'
